{"id":"grape","parent":"heuchera","name":"Grape Soda","longName":"heuchera Grape Soda","description":"\"Amazing rose pink spring leaves are followed by lovely light-purple flowers which flower spring through summer. Summer to winter leaves are purple burnished silver. An outstanding container and front of the border type. Long lasting flowers make this a dual purpose plant.\"","thumbnail":"images/ggn/thumbnail/Heuchera_Grape_Soda_1.jpg","images":["images/ggn/large/Heuchera_Grape_Soda_1b.jpg","images/ggn/large/Heuchera_Grape_Soda_2b.jpg"],"price":"","unit":"","soil":"","growthRate":"Fast","growingSeason":"Spring","floweringSeason":"Spring","bloomTime":"April,May,June,July,August","comments":"","children":[]}